Workbook
Name Slicer_Brand_Name: #N/A
Name Slicer_Country: #N/A
Name Slicer_Last_Updated__Month: #N/A
Name Slicer_Price_with_Currency: #N/A
Name Slicer_Revenue1: #N/A
Name Slicer_Sold: #N/A
Name Timeline_Last_Updated: #N/A

Sheet Descriptive Analysis
A1: Price | B1: Result | C1: Available stock | D1: Result3 | E1: Sold | F1: Result2
A3: Mean | B3: 46.4812 | C3: Mean | D3: 18.307 | E3: Mean | F3: 761.669
A4: Standard Error | B4: 1.1234896 | C4: Standard Error | D4: 2.0527534 | E4: Standard Error | F4: 100.93655
A5: Median | B5: 35.71 | C5: Median | D5: 8 | E5: Median | F5: 48
A6: Mode | B6: 29.99 | C6: Mode | D6: 10 | E6: Mode | F6: 4
A7: Standard Deviation | B7: 35.527862 | C7: Standard Deviation | D7: 64.913762 | E7: Standard Deviation | F7: 3191.8939
A8: Sample Variance | B8: 1262.2289 | C8: Sample Variance | D8: 4213.7965 | E8: Sample Variance | F8: 10188187
A9: Kurtosis | B9: 5.6767954 | C9: Kurtosis | D9: 92.325915 | E9: Kurtosis | F9: 123.59076
A10: Skewness | B10: 2.0390036 | C10: Skewness | D10: 8.7469909 | E10: Skewness | F10: 9.8170504
A11: Range | B11: 256.09 | C11: Range | D11: 900 | E11: Range | F11: 54052
A12: Minimum | B12: 3 | C12: Minimum | D12: 0 | E12: Minimum | F12: 0
A13: Maximum | B13: 259.09 | C13: Maximum | D13: 900 | E13: Maximum | F13: 54052
A14: Sum | B14: 46481.2 | C14: Sum | D14: 18307 | E14: Sum | F14: 761669
A15: Count | B15: 1000 | C15: Count | D15: 1000 | E15: Count | F15: 1000

Sheet match and index
A1: Branded | B1: Type | C1: Price with Currency | D1: Available Stock | E1: Sold | F1: Parfum Quality
A2: Alexandria Eau de Parfum | B2: Eau de Parfum | C2: 3 | D2: 57 | E2: 4 | F2: Normal Quality
A3: Eau de Parfum | B3: Eau de Parfum | C3: 3.5 | D3: 0 | E3: 3009 | F3: High Quality
A4: 2Nd To None | B4: Eau de Parfum | C4: 6.65 | D4: 10 | E4: 18882 | F4: High Quality
A5: Afnan | B5: Eau de Parfum | C5: 6.94 | D5: 10 | E5: 131 | F5: Normal Quality
A6: Secertmu | B6: Eau de Parfum | C6: 6.96 | D6: 3 | E6: 102 | F6: Normal Quality
A7: Secertmu | B7: Eau de Parfum | C7: 6.97 | D7: 10 | E7: 803 | F7: Normal Quality
A8: Unbranded | B8: Car Air Freshener | C8: 7.19 | D8: 10 | E8: 131 | F8: Normal Quality
A9: Pierre Cardin | B9: Eau de Toilette | C9: 7.28 | D9: 3 | E9: 149 | F9: Normal Quality
A10: Dolce & Gabbana | B10: Eau de Parfum | C10: 7.5 | D10: 24 | E10: 115 | F10: Normal Quality
A11: BurberrUnknown | B11: Eau de Toilette | C11: 7.95 | D11: 10 | E11: 254 | F11: Normal Quality
A12: Secertmu | B12: Eau de Parfum | C12: 7.96 | D12: 10 | E12: 38 | F12: Normal Quality
A13: Dvne Eau de Parfum | B13: Body Unknown Oil | C13: 8 | D13: 10 | E13: 1113 | F13: High Quality
A17: MATCH
A18: find the row no. of Brand name | B18: =MATCH("Afnan",A1:A13,0) -> 5
A20: INDEX
A21: Find the term Car air freshner | B21: =INDEX(A2:F13,7,2) -> Car Air Freshener
A22: INDEX AND MATCH
A23: Finding the price of the perfume Secertmu | B23: =INDEX(A1:F13,MATCH("Secertmu",A1:A13,0),3) -> 6.96

Sheet power query
A1: Branded | B1: Type | C1: Price with Currency | D1: Available Stock | E1: Sold | F1: Parfum Quality | G1: Last Updated month | H1: Last Updated Date | I1: Last Updated Year | J1: Last Updated Time | K1: Item Location | L1: City | M1: Country
A2: Alexandria Eau de Parfum | B2: Eau de Parfum | C2: 3 | D2: 57 | E2: 4 | F2: Normal Quality | G2: March | H2: 23 | I2: 2024 | J2: 0.75828704 | K2: Wynnewood | L2: pennsylvania | M2: United States
A3: Eau de Parfum | B3: Eau de Parfum | C3: 3.5 | D3: 0 | E3: 3009 | F3: High Quality | G3: March | H3: 23 | I3: 2024 | J3: 0.39170139 | K3: Pearland | L3: Texas | M3: United States
A4: 2Nd To None | B4: Eau de Parfum | C4: 6.65 | D4: 10 | E4: 18882 | F4: High Quality | G4: March | H4: 21 | I4: 2024 | J4: 0.80195602 | K4: Lagrange | L4: Georgia | M4: United States
A5: Afnan | B5: Eau de Parfum | C5: 6.94 | D5: 10 | E5: 131 | F5: Normal Quality | G5: March | H5: 20 | I5: 2024 | J5: 0.59065972 | K5: Midway City | L5: California | M5: United States
A6: Secertmu | B6: Eau de Parfum | C6: 6.96 | D6: 3 | E6: 102 | F6: Normal Quality | G6: March | H6: 18 | I6: 2024 | J6: 0.67761574 | K6: San Francisco | L6: California | M6: United States
A7: Secertmu | B7: Eau de Parfum | C7: 6.97 | D7: 10 | E7: 803 | F7: Normal Quality | G7: March | H7: 21 | I7: 2024 | J7: 0.80570602 | K7: San Francisco | L7: California | M7: United States
A8: Unbranded | B8: Car Air Freshener | C8: 7.19 | D8: 10 | E8: 131 | F8: Normal Quality | G8: Apr | H8: 17 | I8: 2024 | J8: 0.98743056 | K8: Houston | L8: Texas | M8: United States
A9: Pierre Cardin | B9: Eau de Toilette | C9: 7.28 | D9: 3 | E9: 149 | F9: Normal Quality | G9: March | H9: 21 | I9: 2024 | J9: 0.82761574 | K9: Miami | L9: Florida | M9: United States
A10: Dolce & Gabbana | B10: Eau de Parfum | C10: 7.5 | D10: 24 | E10: 115 | F10: Normal Quality | G10: Apr | H10: 5 | I10: 2024 | J10: 0.036886574 | K10: Albany | L10: New York | M10: United States
A11: BurberrUnknown | B11: Eau de Toilette | C11: 7.95 | D11: 10 | E11: 254 | F11: Normal Quality | G11: March | H11: 24 | I11: 2024 | J11: 0.022962963 | K11: Phillipsburg | L11: New York | M11: United States
A12: Secertmu | B12: Eau de Parfum | C12: 7.96 | D12: 10 | E12: 38 | F12: Normal Quality | G12: Feb | H12: 22 | I12: 2024 | J12: 0.089502315 | K12: San Francisco | L12: California | M12: United States
A13: DvUnknownne Eau de Parfum | B13: BodUnknown Oil | C13: 8 | D13: 10 | E13: 1113 | F13: High Quality | G13: March | H13: 22 | I13: 2024 | J13: 0.34869213 | K13: Fort Lauderdale | L13: Florida | M13: United States
... A1001: Creed | B1001: Eau de Parfum | C1001: 259.09 | D1001: 3 | E1001: 456 | F1001: Normal Quality | G1001: March | H1001: 24 | I1001: 2024 | J1001: 0.35700231 | K1001: Edison | L1001: New York | M1001: United States

Sheet brand  Name vs Quantity sold
A3: Brand Name | B3: Sum of Sold
A4: Abercrombie & Fitch | B4: 381
A5: Al Wataniah | B5: 36
A6: Armaf | B6: 10
A7: As Picture Show | B7: 44
A8: As Shown | B8: 11
A9: Avon | B9: 37
A10: Bath & BodUnknown Works | B10: 35
A11: BUnknown Al Hambra | B11: 79
A12: Calvin Klein | B12: 189
A13: Carolina Herrera | B13: 17
A14: Chanel | B14: 286
A15: Claude Marsal | B15: 9
... A50: Grand Total | B50: 6488

Sheet Country vs price with currency
A3: Country | B3: Sum of Price with Currency
A4: India | B4: 124.35
A5: Grand Total | B5: 124.35

Sheet parfum_quality_revenue
A3: Sum of Revenue | B3: Parfum Quality
A4: Type of Parfum | B4: Normal Quality | C4: Grand Total
A5: Car Air Freshener | B5: 941.89 | C5: 941.89
A6: Eau de Cologne | B6: 21145.14 | C6: 21145.14
A7: Eau de Parfum | B7: 60034.29 | C7: 60034.29
A8: Eau de Toilette | B8: 38480.5 | C8: 38480.5
A9: Roll On | B9: 939.06 | C9: 939.06
A10: Grand Total | B10: 121540.88 | C10: 121540.88
A24: Dsecriptive Statistics

Sheet Dashboard
H3: PARFUM SALES DASHBOARD

Sheet last updated Year_revenue
A2: Last updated year_Revenue_Country | B2: All
A4: Sum of Revenue | B4: Last updated year
B5: Hong Kong | C5: United States | F5: Grand Total
B6: 2024 | C6: 2024 | D6: 2023 | E6: 2022 | K6: Descriptive Statistics
K7: ●Calvin Klein is the highly sold ●United States has the highest markable sales
A8: Brand Name
A9: Abercrombie & Fitch | C9: 19046.19 | F9: 19046.19
A10: Al Wataniah | C10: 1260 | F10: 1260 | K10: Diagnostic Statistics
A11: Armaf | C11: 850 | F11: 850 | K11: ●Probably United states people prefer this parfum than other countries
A12: As Picture Show | C12: 3079.56 | F12: 3079.56
A13: As Shown | B13: 769.89 | F13: 769.89
A14: Avon | C14: 1905.13 | F14: 1905.13
A15: Bath & BodUnknown Works | C15: 2098.95 | F15: 2098.95
A16: BUnknown Al Hambra | C16: 2003 | F16: 2003 | M16: Pivot table linked with Pivot Chart
A17: Calvin Klein | C17: 4148.55 | F17: 4148.55
A18: Carolina Herrera | C18: 1121.83 | F18: 1121.83
A19: Chanel | C19: 6292 | F19: 6292
A20: Claude Marsal | C20: 1620 | F20: 1620
A21: Creed | C21: 478.5 | F21: 478.5
A22: Dana | C22: 9698.53 | F22: 9698.53
A23: Diesel | C23: 475.72 | F23: 475.72
A24: Dior | C24: 1903.72 | F24: 1903.72
A25: Dolce & Gabbana | C25: 8584.5 | F25: 8584.5
A26: Dolce&Gabbana | C26: 701.91 | F26: 701.91
A27: Dossier | C27: 320 | F27: 320
A28: Eau de Cologne | D28: 6586.9 | F28: 6586.9
A29: Ed HardUnknown | C29: 573.3 | F29: 573.3
A30: Estee Lauder | C30: 419.76 | F30: 419.76
A31: Fc | C31: 1749.3 | F31: 1749.3
A32: Fragrance Couture | C32: 3085.88 | F32: 3085.88
A33: Giorgio Armani | C33: 1455.72 | F33: 1455.72
A34: Guerlain | C34: 2279.76 | F34: 2279.76
A35: Have A Scent | C35: 939.06 | F35: 939.06 | M35: Combo Chart
A36: Hermès | C36: 7799.43 | F36: 7799.43
A37: Hugo Boss | C37: 1346.25 | F37: 1346.25
A38: Jil Sander | C38: 2366.4 | F38: 2366.4
A39: Lalique | C39: 12493.59 | F39: 12493.59
A40: Lapidus | C40: 10401.44 | F40: 10401.44
A41: Louis Vuitton | C41: 14848.65 | F41: 14848.65
A42: Macarena | C42: 2438.78 | F42: 2438.78
A43: Maison Martin Margiela | B43: 439.89 | F43: 439.89
A44: Mancera | C44: 229.5 | F44: 229.5
A45: Mandarin Duck | E45: 2099.25 | F45: 2099.25
A46: Paco Rabanne | C46: 909.87 | F46: 909.87
A47: Polo Ralph Lauren | C47: 3003.94 | F47: 3003.94
A48: Prada | C48: 798.48 | F48: 798.48
A49: Ralph Lauren | C49: 439.92 | F49: 439.92
A50: Secertmu | C50: 302.48 | F50: 302.48
A51: The Baron | D51: 34.99 | F51: 34.99
A52: Unbranded | C52: 1179.72 | F52: 1179.72
A53: Unknownsl | C53: 599.88 | F53: 599.88
A54: Unknownves Saint Laurent | C54: 1443.81 | D54: 1169.55 | F54: 2613.36
A55: Grand Total | B55: 1209.78 | C55: 136693.01 | D55: 7791.44 | E55: 2099.25 | F55: 147793.48

Sheet Country vs Available stock
A3: Country | B3: Sum of Available Stock
A4: China | B4: 6
A5: Hong Kong | B5: 10
A6: United States | B6: 1688
A7: Grand Total | B7: 1704

Sheet Month vs revenue
A3: Month | B3: Average of Revenue
A4: Jan | B4: 4098.565
A5: Feb | B5: 2146.9629
A6: Apr | B6: 2826.5321
A7: Sep | B7: 1169.55
A8: Nov | B8: 2907.0467
A9: Grand Total | B9: 2761.74

Sheet Mens perfume 
A1: Brand Name | B1: Type | C1: Price with Currency | D1: Available Stock | E1: Sold | F1: Revenue | G1: Parfum Quality | H1: Last Updated | I1: Item Location | J1: City | K1: Country
A2: Dolce&Gabbana | B2: Eau de Toilette | C2: 54.99 | D2: 0 | E2: 45 | F2: =C:C*E:E -> 2474.55 | G2: =IF(Table2[[#This Row],[Sold]]>1000,"High Quality","Normal Quality") -> Normal Quality | H2: 44854.768 | I2: Bellaire | J2: Texas | K2: United States
A3: Mandarin Duck | B3: Eau de Toilette | C3: 27.99 | D3: 0 | E3: 75 | F3: =C:C*E:E -> 2099.25 | G3: =IF(Table2[[#This Row],[Sold]]>1000,"High Quality","Normal Quality") -> Normal Quality | H3: 44867.127 | I3: Edison | J3: New York | K3: United States
A4: Unknownves Saint Laurent | B4: Eau de Toilette | C4: 16.95 | D4: 8 | E4: 69 | F4: =C:C*E:E -> 1169.55 | G4: =IF(Table2[[#This Row],[Sold]]>1000,"High Quality","Normal Quality") -> Normal Quality | H4: 45184.273 | I4: Stafford | J4: Texas | K4: United States | M4: SUMMARY
A5: The Baron | B5: Eau de Cologne | C5: 34.99 | D5: 8 | E5: 1 | F5: =C:C*E:E -> 34.99 | G5: =IF(Table2[[#This Row],[Sold]]>1000,"High Quality","Normal Quality") -> Normal Quality | H5: 45242.513 | I5: Canton | J5: Michigan | K5: United States
A6: Eau de Cologne | B6: Eau de Parfum | C6: 19.9 | D6: 0 | E6: 331 | F6: =C:C*E:E -> 6586.9 | G6: =IF(Table2[[#This Row],[Sold]]>1000,"High Quality","Normal Quality") -> Normal Quality | H6: 45251.356 | I6: Stony Brook | J6: New York | K6: United States
A7: Avon | B7: Eau de Cologne | C7: 51.49 | D7: 6 | E7: 37 | F7: =C:C*E:E -> 1905.13 | G7: =IF(Table2[[#This Row],[Sold]]>1000,"High Quality","Normal Quality") -> Normal Quality | H7: 45299.735 | I7: Humacao | J7: Puerto Rico | K7: United States | M7: Basic Functions (Part 1) | N7: Details | O7: Result
A8: Chanel | B8: Eau de Toilette | C8: 22 | D8: 10 | E8: 286 | F8: =C:C*E:E -> 6292 | G8: =IF(Table2[[#This Row],[Sold]]>1000,"High Quality","Normal Quality") -> Normal Quality | H8: 45301.597 | I8: Albany | J8: New York | K8: United States | M8: sum() | N8: sum of price | O8: =SUM(B:B) -> 0
A9: Hermès | B9: Eau de Toilette | C9: 39.99 | D9: 3 | E9: 40 | F9: =C:C*E:E -> 1599.6 | G9: =IF(Table2[[#This Row],[Sold]]>1000,"High Quality","Normal Quality") -> Normal Quality | H9: 45330.446 | I9: Miami | J9: Florida | K9: United States | M9: Average() | N9: Average amount of product sold | O9: =AVERAGE(D:D) -> 18.307
A10: Dana | B10: Eau de Cologne | C10: 14.99 | D10: 9 | E10: 647 | F10: =C:C*E:E -> 9698.53 | G10: =IF(Table2[[#This Row],[Sold]]>1000,"High Quality","Normal Quality") -> Normal Quality | H10: 45338.857 | I10: Orlando | J10: Florida | K10: United States | M10: Min() | N10: Minimum sold product price | O10: =MIN(D:D) -> 0
A11: Claude Marsal | B11: Eau de Parfum | C11: 180 | D11: 0 | E11: 9 | F11: =C:C*E:E -> 1620 | G11: =IF(Table2[[#This Row],[Sold]]>1000,"High Quality","Normal Quality") -> Normal Quality | H11: 45343.672 | I11: Orlando | J11: Florida | K11: United States | M11: Max() | N11: Maximun sold price | O11: =MAX(B:B) -> 0
A12: Secertmu | B12: Eau de Parfum | C12: 7.96 | D12: 10 | E12: 38 | F12: =C:C*E:E -> 302.48 | G12: =IF(Table2[[#This Row],[Sold]]>1000,"High Quality","Normal Quality") -> Normal Quality | H12: 45344.09 | I12: San Francisco | J12: California | K12: United States | M12: Count() | N12: count the no. of price details | O12: =COUNT(B:B) -> 0
A13: Creed | B13: Eau de Parfum | C13: 15.95 | D13: 3 | E13: 30 | F13: =C:C*E:E -> 478.5 | G13: =IF(Table2[[#This Row],[Sold]]>1000,"High Quality","Normal Quality") -> Normal Quality | H13: 45348.523 | I13: Midway City | J13: California | K13: United States | M13: Counta() | N13: count the text no. in item location | O13: =COUNTA(G:G) -> 1001
A14: Paco Rabanne | B14: Eau de Parfum | C14: 69.99 | D14: 10 | E14: 13 | F14: =C:C*E:E -> 909.87 | G14: =IF(Table2[[#This Row],[Sold]]>1000,"High Quality","Normal Quality") -> Normal Quality | H14: 45350.31 | I14: Keyport | J14: New York | K14: United States
A15: Estee Lauder | B15: Eau de Cologne | C15: 17.49 | D15: 0 | E15: 24 | F15: =C:C*E:E -> 419.76 | G15: =IF(Table2[[#This Row],[Sold]]>1000,"High Quality","Normal Quality") -> Normal Quality | H15: 45350.31 | I15: Keyport | J15: New York | K15: United States
A16: Moschino | B16: Eau de Parfum | C16: 39.95 | D16: 2 | E16: 5 | F16: =C:C*E:E -> 199.75 | G16: =IF(Table2[[#This Row],[Sold]]>1000,"High Quality","Normal Quality") -> Normal Quality | H16: 45352.415 | I16: Huntington Station | J16: New York | K16: United States | M16: Basic Function (Part 2) | N16: Details | O16: Result
A17: Paco Rabanne | B17: Eau de Toilette | C17: 18.99 | D17: 10 | E17: 38 | F17: =C:C*E:E -> 721.62 | G17: =IF(Table2[[#This Row],[Sold]]>1000,"High Quality","Normal Quality") -> Normal Quality | H17: 45352.486 | I17: Brooklyn | J17: New York | K17: United States | M17: Sumif() | N17: calculated the Eau de toilette price Range | O17: =SUMIF(A:A,"Eau De Toilette",B:B) -> 0
A18: Polo Ralph Lauren | B18: Eau de Parfum | C18: 103.2 | D18: 54 | E18: 5 | F18: =C:C*E:E -> 516 | G18: =IF(Table2[[#This Row],[Sold]]>1000,"High Quality","Normal Quality") -> Normal Quality | H18: 45352.633 | I18: Seattle | J18: Washington | K18: United States | M18: Countif() | N18: counted the no. of Eau de parfum | O18: =COUNTIF(A:A,"Eau de Parfum") -> 3
A19: TiffanUnknown | B19: Eau de Toilette | C19: 49.99 | D19: 10 | E19: 19 | F19: =C:C*E:E -> 949.81 | G19: =IF(Table2[[#This Row],[Sold]]>1000,"High Quality","Normal Quality") -> Normal Quality | H19: 45352.973 | I19: California Or Hong Kong | J19: Hong Kong | K19: United States | M19: Averageif() | N19: found out the average for DIOR parfum sold | O19: =AVERAGEIF(Table2[[ Brand Name]],"Dior",Table2[Sold]) -> 275.18182
A20: Rochas | B20: Eau de Toilette | C20: 24.55 | D20: 10 | E20: 433 | F20: =C:C*E:E -> 10630.15 | G20: =IF(Table2[[#This Row],[Sold]]>1000,"High Quality","Normal Quality") -> Normal Quality | H20: 45353.063 | I20: Dallas | J20: Texas | K20: United States | M20: if() | N20: if(sold no.>1000,"High Quality","Normal Quality") | O20: Parfum Quality column is created
A21: Hugo Boss | B21: Eau de Parfum | C21: 65.37 | D21: 4 | E21: 87 | F21: =C:C*E:E -> 5687.19 | G21: =IF(Table2[[#This Row],[Sold]]>1000,"High Quality","Normal Quality") -> Normal Quality | H21: 45353.063 | I21: Dallas | J21: Texas | K21: United States
A22: MUnknownrurgia | B22: Eau de Toilette | C22: 9.21 | D22: 0 | E22: 3093 | F22: =C:C*E:E -> 28486.53 | G22: =IF(Table2[[#This Row],[Sold]]>1000,"High Quality","Normal Quality") -> High Quality | H22: 45353.063 | I22: Dallas | J22: Texas | K22: United States
A23: Eau de Cologne | B23: Eau de Toilette | C23: 19.9 | D23: 10 | E23: 294 | F23: =C:C*E:E -> 5850.6 | G23: =IF(Table2[[#This Row],[Sold]]>1000,"High Quality","Normal Quality") -> Normal Quality | H23: 45353.575 | I23: Rochester | J23: New York | K23: United States | M23: Text Functions | N23: Details | O23: Result
A24: Dolce&Gabbana | B24: Eau de Parfum | C24: 91 | D24: 47 | E24: 1 | F24: =C:C*E:E -> 91 | G24: =IF(Table2[[#This Row],[Sold]]>1000,"High Quality","Normal Quality") -> Normal Quality | H24: 45353.817 | I24: Manor | J24: Texas | K24: United States | M24: left() | N24: took the 1st 3 letters from country column | O24: =LEFT(K25,3) -> Uni
A25: Eau de Cologne | B25: Eau de Cologne | C25: 41.99 | D25: 10 | E25: 15 | F25: =C:C*E:E -> 629.85 | G25: =IF(Table2[[#This Row],[Sold]]>1000,"High Quality","Normal Quality") -> Normal Quality | H25: 45353.876 | I25: Fredericksburg | J25: Virginia | K25: United States | M25: right() | N25: took the last 4 letters from city column | O25: =RIGHT(J17,4) -> York
A26: GivenchUnknown | B26: Eau de Parfum | C26: 70 | D26: 0 | E26: 2 | F26: =C:C*E:E -> 140 | G26: =IF(Table2[[#This Row],[Sold]]>1000,"High Quality","Normal Quality") -> Normal Quality | H26: 45354.489 | I26: Franklin Square | J26: New York | K26: United States | M26: mid() | N26: took the mid 6 letters from item location column | O26: =MID(I22,3,6) -> llas
A27: Bharara | B27: Eau de Parfum | C27: 78.99 | D27: 10 | E27: 142 | F27: =C:C*E:E -> 11216.58 | G27: =IF(Table2[[#This Row],[Sold]]>1000,"High Quality","Normal Quality") -> Normal Quality | H27: 45354.615 | I27: Miami | J27: Florida | K27: United States | M27: upper() | N27: did the upper function in city column | O27: =UPPER(J18) -> WASHINGTON
A28: Estée Lauder | B28: Eau de Cologne | C28: 19.99 | D28: 5 | E28: 10 | F28: =C:C*E:E -> 199.9 | G28: =IF(Table2[[#This Row],[Sold]]>1000,"High Quality","Normal Quality") -> Normal Quality | H28: 45354.747 | I28: New York | J28: New York | K28: United States | M28: lower() | N28: did the lower() in country column | O28: =LOWER(K26) -> united states
A29: Roberto Cavalli | B29: Eau de Toilette | C29: 42.95 | D29: 2 | E29: 8 | F29: =C:C*E:E -> 343.6 | G29: =IF(Table2[[#This Row],[Sold]]>1000,"High Quality","Normal Quality") -> Normal Quality | H29: 45355.211 | I29: Keyport | J29: New York | K29: United States | M29: proper() | N29: did the proper() in country column | O29: =PROPER(J62) -> New York
A30: Roja | B30: Eau de Parfum | C30: 109.99 | D30: 10 | E30: 26 | F30: =C:C*E:E -> 2859.74 | G30: =IF(Table2[[#This Row],[Sold]]>1000,"High Quality","Normal Quality") -> Normal Quality | H30: 45355.248 | I30: Rowland Heights | J30: California | K30: United States
A31: GuUnknown Laroche | B31: Eau de Toilette | C31: 19.99 | D31: 0 | E31: 58 | F31: =C:C*E:E -> 1159.42 | G31: =IF(Table2[[#This Row],[Sold]]>1000,"High Quality","Normal Quality") -> Normal Quality | H31: 45355.259 | I31: East Meadow | J31: New York | K31: United States
A32: Calvin Klein | B32: Eau de Toilette | C32: 28.99 | D32: 7 | E32: 124 | F32: =C:C*E:E -> 3594.76 | G32: =IF(Table2[[#This Row],[Sold]]>1000,"High Quality","Normal Quality") -> Normal Quality | H32: 45356.057 | I32: Edison | J32: New York | K32: United States
A33: Falic Fashion Group | B33: Eau de Toilette | C33: 29.98 | D33: 10 | E33: 14 | F33: =C:C*E:E -> 419.72 | G33: =IF(Table2[[#This Row],[Sold]]>1000,"High Quality","Normal Quality") -> Normal Quality | H33: 45356.392 | I33: Burlington | J33: Ontario | K33: Canada | M33: Data Validation and Cleaning Intro
A34: Roja Dove | B34: Eau de Parfum | C34: 129.99 | D34: 10 | E34: 25 | F34: =C:C*E:E -> 3249.75 | G34: =IF(Table2[[#This Row],[Sold]]>1000,"High Quality","Normal Quality") -> Normal Quality | H34: 45356.769 | I34: Pomona | J34: California | K34: United States | M34: Drop down list is activated in parfum Quality and in Item location column
A35: Penhaligon'S | B35: Eau de Parfum | C35: 188.99 | D35: 10 | E35: 1 | F35: =C:C*E:E -> 188.99 | G35: =IF(Table2[[#This Row],[Sold]]>1000,"High Quality","Normal Quality") -> Normal Quality | H35: 45356.799 | I35: Ottawa | J35: Canada | K35: Canada | M35: Duplicates are removed
A36: Unbranded | B36: Eau de Toilette | C36: 39.99 | D36: 10 | E36: 18 | F36: =C:C*E:E -> 719.82 | G36: =IF(Table2[[#This Row],[Sold]]>1000,"High Quality","Normal Quality") -> Normal Quality | H36: 45356.965 | I36: California | J36: United States | K36: Hong Kong | M36: Blank cells are handled using filters and formula(if(isblank)
A37: Dossier | B37: Eau de Parfum | C37: 20 | D37: 5 | E37: 16 | F37: =C:C*E:E -> 320 | G37: =IF(Table2[[#This Row],[Sold]]>1000,"High Quality","Normal Quality") -> Normal Quality | H37: 45356.971 | I37: Los Angeles | J37: California | K37: United States
A38: Dossier | B38: Eau de Parfum | C38: 29 | D38: 0 | E38: 19 | F38: =C:C*E:E -> 551 | G38: =IF(Table2[[#This Row],[Sold]]>1000,"High Quality","Normal Quality") -> Normal Quality | H38: 45356.971 | I38: Los Angeles | J38: California | K38: United States | M38: POWER QUERY
A39: Bvlgari | B39: Eau de Parfum | C39: 29.99 | D39: 65 | E39: 25 | F39: =C:C*E:E -> 749.75 | G39: =IF(Table2[[#This Row],[Sold]]>1000,"High Quality","Normal Quality") -> Normal Quality | H39: 45357 | I39: Keyport | J39: New York | K39: United States | M39: The dataset was loaded into power Query and the Last updated time,month,year,date are splitted into separate coloumns and reloaded.
A40: Dior | B40: Eau de Toilette | C40: 84.99 | D40: 9 | E40: 51 | F40: =C:C*E:E -> 4334.49 | G40: =IF(Table2[[#This Row],[Sold]]>1000,"High Quality","Normal Quality") -> Normal Quality | H40: 45357.195 | I40: Sterling Heights | J40: Michigan | K40: United States
A41: Unknownves Saint Laurent | B41: Eau de Parfum | C41: 129 | D41: 26 | E41: 13 | F41: =C:C*E:E -> 1677 | G41: =IF(Table2[[#This Row],[Sold]]>1000,"High Quality","Normal Quality") -> Normal Quality | H41: 45357.516 | I41: Mclean | J41: Virginia | K41: United States
A42: Mirage Brands | B42: Eau de Toilette | C42: 13.68 | D42: 47 | E42: 105 | F42: =C:C*E:E -> 1436.4 | G42: =IF(Table2[[#This Row],[Sold]]>1000,"High Quality","Normal Quality") -> Normal Quality | H42: 45357.701 | I42: Cumming | J42: Georgia | K42: United States | M42: HANDLING INCONSISTENT DATA
A43: Metaherbal Labs | B43: Unscented | C43: 39.95 | D43: 10 | E43: 353 | F43: =C:C*E:E -> 14102.35 | G43: =IF(Table2[[#This Row],[Sold]]>1000,"High Quality","Normal Quality") -> Normal Quality | H43: 45357.793 | I43: Orange | J43: Connecticut | K43: United States
A44: ReUnknownane Tradition | B44: Eau de Toilette | C44: 25.96 | D44: 0 | E44: 214 | F44: =C:C*E:E -> 5555.44 | G44: =IF(Table2[[#This Row],[Sold]]>1000,"High Quality","Normal Quality") -> Normal Quality | H44: 45357.888 | I44: Dallas | J44: Texas | K44: United States | M44: 1.Using trim(),the country column was arranged
A45: Kenneth Cole | B45: Eau de Toilette | C45: 18.66 | D45: 10 | E45: 58 | F45: =C:C*E:E -> 1082.28 | G45: =IF(Table2[[#This Row],[Sold]]>1000,"High Quality","Normal Quality") -> Normal Quality | H45: 45357.978 | I45: Dallas | J45: Texas | K45: United States | M45: 2.using text to column,the item location coloumn was splitted
A46: Kenneth Cole | B46: Eau de Toilette | C46: 24.5 | D46: 10 | E46: 415 | F46: =C:C*E:E -> 10167.5 | G46: =IF(Table2[[#This Row],[Sold]]>1000,"High Quality","Normal Quality") -> Normal Quality | H46: 45358.325 | I46: Orlando | J46: Florida | K46: United States | M46: 3.using Flashfill(),the blank values are filled
A47: CotUnknown | B47: Eau de Cologne | C47: 16.9 | D47: 10 | E47: 34 | F47: =C:C*E:E -> 574.6 | G47: =IF(Table2[[#This Row],[Sold]]>1000,"High Quality","Normal Quality") -> Normal Quality | H47: 45358.464 | I47: Midway City | J47: California | K47: United States
A48: As Shown | B48: Eau de Toilette | C48: 40.99 | D48: 10 | E48: 17 | F48: =C:C*E:E -> 696.83 | G48: =IF(Table2[[#This Row],[Sold]]>1000,"High Quality","Normal Quality") -> Normal Quality | H48: 45359.072 | I48: Nevada/California | J48: USA | K48: Hong Kong
A49: Paco Rabanne | B49: Eau de Parfum | C49: 11.95 | D49: 93 | E49: 18 | F49: =C:C*E:E -> 215.1 | G49: =IF(Table2[[#This Row],[Sold]]>1000,"High Quality","Normal Quality") -> Normal Quality | H49: 45359.134 | I49: Pearland | J49: Texas | K49: United States | M49: CONDITIONAL FORMATTING
A50: Unknownsl | B50: Eau de Toilette | C50: 38 | D50: 8 | E50: 42 | F50: =C:C*E:E -> 1596 | G50: =IF(Table2[[#This Row],[Sold]]>1000,"High Quality","Normal Quality") -> Normal Quality | H50: 45359.154 | I50: Wakefield | J50: Massachusetts | K50: Hong Kong | M50: Flags,bars are used to visualise the data status
A51: GivenchUnknown | B51: Eau de Parfum | C51: 73.52 | D51: 0 | E51: 8 | F51: =C:C*E:E -> 588.16 | G51: =IF(Table2[[#This Row],[Sold]]>1000,"High Quality","Normal Quality") -> Normal Quality | H51: 45359.251 | I51: Dallas | J51: Texas | K51: United States
A52: IsseUnknown MiUnknownake | B52: Eau de Toilette | C52: 44.61 | D52: 6 | E52: 27 | F52: =C:C*E:E -> 1204.47 | G52: =IF(Table2[[#This Row],[Sold]]>1000,"High Quality","Normal Quality") -> Normal Quality | H52: 45359.326 | I52: Dallas | J52: Texas | K52: United States | M52: DESCRIPTIVE ANALYSIS
A53: Prada | B53: Eau de Toilette | C53: 68.55 | D53: 4 | E53: 65 | F53: =C:C*E:E -> 4455.75 | G53: =IF(Table2[[#This Row],[Sold]]>1000,"High Quality","Normal Quality") -> Normal Quality | H53: 45359.335 | I53: Middle Grove | J53: New York | K53: United States
A54: MarUnknown KaUnknown | B54: Eau de Cologne | C54: 30 | D54: 10 | E54: 24 | F54: =C:C*E:E -> 720 | G54: =IF(Table2[[#This Row],[Sold]]>1000,"High Quality","Normal Quality") -> Normal Quality | H54: 45359.359 | I54: Douglasville | J54: Georgia | K54: United States | M54: It was mentioned in a separate worksheet
A55: Bvlgari | B55: Eau de Parfum | C55: 64.99 | D55: 6 | E55: 15 | F55: =C:C*E:E -> 974.85 | G55: =IF(Table2[[#This Row],[Sold]]>1000,"High Quality","Normal Quality") -> Normal Quality | H55: 45359.391 | I55: Miami | J55: Florida | K55: United States
A56: Ralph Lauren | B56: Eau de Toilette | C56: 44.99 | D56: 4 | E56: 27 | F56: =C:C*E:E -> 1214.73 | G56: =IF(Table2[[#This Row],[Sold]]>1000,"High Quality","Normal Quality") -> Normal Quality | H56: 45359.43 | I56: Miami | J56: Florida | K56: United States
A57: GivenchUnknown | B57: Eau de Toilette | C57: 44.99 | D57: 7 | E57: 32 | F57: =C:C*E:E -> 1439.68 | G57: =IF(Table2[[#This Row],[Sold]]>1000,"High Quality","Normal Quality") -> Normal Quality | H57: 45359.439 | I57: Miami | J57: Florida | K57: United States | M57: FILTERING,SORTING AND EXPLORING THE DATA
A58: Giorgio Armani | B58: Eau de Toilette | C58: 64.99 | D58: 10 | E58: 235 | F58: =C:C*E:E -> 15272.65 | G58: =IF(Table2[[#This Row],[Sold]]>1000,"High Quality","Normal Quality") -> Normal Quality | H58: 45359.466 | I58: Miami | J58: Florida | K58: United States
A59: Paco Rabanne | B59: Eau de toilette | C59: 39.99 | D59: 3 | E59: 3 | F59: =C:C*E:E -> 119.97 | G59: =IF(Table2[[#This Row],[Sold]]>1000,"High Quality","Normal Quality") -> Normal Quality | H59: 45359.604 | I59: New York | J59: United States | K59: United States | M59: 1.Price column is sorted from A to Z
A60: Axe | B60: Eau de Parfum | C60: 11.99 | D60: 6 | E60: 15 | F60: =C:C*E:E -> 179.85 | G60: =IF(Table2[[#This Row],[Sold]]>1000,"High Quality","Normal Quality") -> Normal Quality | H60: 45359.653 | I60: Euless | J60: Texas | K60: United States | M60: 2.Filter is used to visualize India from country column
A61: BurberrUnknown | B61: Eau de Toilette | C61: 28.99 | D61: 10 | E61: 7 | F61: =C:C*E:E -> 202.93 | G61: =IF(Table2[[#This Row],[Sold]]>1000,"High Quality","Normal Quality") -> Normal Quality | H61: 45359.657 | I61: Katy | J61: Texas | K61: United States
A62: Creed | B62: Oil | C62: 9.96 | D62: 3 | E62: 266 | F62: =C:C*E:E -> 2649.36 | G62: =IF(Table2[[#This Row],[Sold]]>1000,"High Quality","Normal Quality") -> Normal Quality | H62: 45359.776 | I62: Jamaica | J62: New York | K62: United States | M62: Top 5 from sold | N62: Bottom 5 from price
A63: Ralph Lauren | B63: Eau de Parfum | C63: 12.99 | D63: 7 | E63: 5 | F63: =C:C*E:E -> 64.95 | G63: =IF(Table2[[#This Row],[Sold]]>1000,"High Quality","Normal Quality") -> Normal Quality | H63: 45360.204 | I63: Brooklyn | J63: New York | K63: United States | M63: 30655 | N63: 23.34
A64: HUnknownbrid & CompanUnknown | B64: Eau de Parfum | C64: 24.19 | D64: 2 | E64: 73 | F64: =C:C*E:E -> 1765.87 | G64: =IF(Table2[[#This Row],[Sold]]>1000,"High Quality","Normal Quality") -> Normal Quality | H64: 45360.344 | I64: Temple | J64: Texas | K64: United States | M64: 24048 | N64: 28.75
A65: Hugo Boss | B65: Eau de Toilette | C65: 47.26 | D65: 3 | E65: 52 | F65: =C:C*E:E -> 2457.52 | G65: =IF(Table2[[#This Row],[Sold]]>1000,"High Quality","Normal Quality") -> Normal Quality | H65: 45360.483 | I65: Dallas | J65: Texas | K65: United States | M65: 54052 | N65: 27.94
A66: Liz Claiborne | B66: Eau de Toilette | C66: 17.02 | D66: 0 | E66: 3823 | F66: =C:C*E:E -> 65067.46 | G66: =IF(Table2[[#This Row],[Sold]]>1000,"High Quality","Normal Quality") -> High Quality | H66: 45360.669 | I66: Dallas | J66: Texas | K66: United States | M66: 31718 | N66: 32.5
A67: Eau de Parfum | B67: Eau de Parfum | C67: 17.95 | D67: 0 | E67: 4 | F67: =C:C*E:E -> 71.8 | G67: =IF(Table2[[#This Row],[Sold]]>1000,"High Quality","Normal Quality") -> Normal Quality | H67: 45360.721 | I67: Orange City | J67: Florida | K67: United States | M67: 40130 | N67: 14.99
A68: Ebc | B68: Eau de Cologne | C68: 13.5 | D68: 0 | E68: 17 | F68: =C:C*E:E -> 229.5 | G68: =IF(Table2[[#This Row],[Sold]]>1000,"High Quality","Normal Quality") -> Normal Quality | H68: 45360.741 | I68: Hialeah | J68: Florida | K68: United States | N68: 45.95
A69: Calvin Klein | B69: Eau de Parfum | C69: 21.27 | D69: 10 | E69: 30 | F69: =C:C*E:E -> 638.1 | G69: =IF(Table2[[#This Row],[Sold]]>1000,"High Quality","Normal Quality") -> Normal Quality | H69: 45360.867 | I69: Rowland Heights | J69: California | K69: United States
A70: Zara | B70: Eau de Toilette | C70: 15 | D70: 21 | E70: 3 | F70: =C:C*E:E -> 45 | G70: =IF(Table2[[#This Row],[Sold]]>1000,"High Quality","Normal Quality") -> Normal Quality | H70: 45360.885 | I70: Houston | J70: Texas | K70: United States | M70: DATE AND TIME() | N70: RESULT
A71: Unbranded | B71: Eau de Toilette | C71: 25.89 | D71: 9 | E71: 4 | F71: =C:C*E:E -> 103.56 | G71: =IF(Table2[[#This Row],[Sold]]>1000,"High Quality","Normal Quality") -> Normal Quality | H71: 45360.943 | I71: Brooklyn | J71: New York | K71: United States | M71: TODAY() | N71: =TODAY() -> 45982
A72: Ralph Lauren | B72: Eau de Cologne | C72: 29.99 | D72: 110 | E72: 60 | F72: =C:C*E:E -> 1799.4 | G72: =IF(Table2[[#This Row],[Sold]]>1000,"High Quality","Normal Quality") -> Normal Quality | H72: 45361.305 | I72: Miami | J72: Florida | K72: United States | M72: NOW() | N72: =NOW() -> 45982.076
A73: Lacoste | B73: Eau de Toilette | C73: 32.5 | D73: 8 | E73: 634 | F73: =C:C*E:E -> 20605 | G73: =IF(Table2[[#This Row],[Sold]]>1000,"High Quality","Normal Quality") -> Normal Quality | H73: 45361.431 | I73: Dallas | J73: Texas | K73: United States | M73: YEAR() | N73: =YEAR(N71) -> 2025
A74: Carolina Herrera | B74: Eau de Toilette | C74: 39.99 | D74: 4 | E74: 19 | F74: =C:C*E:E -> 759.81 | G74: =IF(Table2[[#This Row],[Sold]]>1000,"High Quality","Normal Quality") -> Normal Quality | H74: 45361.458 | I74: Detroit | J74: Michigan | K74: United States | M74: MONTH() | N74: =MONTH(N71) -> 11
A75: John Varvatos | B75: Eau de Parfum | C75: 79.99 | D75: 15 | E75: 17 | F75: =C:C*E:E -> 1359.83 | G75: =IF(Table2[[#This Row],[Sold]]>1000,"High Quality","Normal Quality") -> Normal Quality | H75: 45361.738 | I75: El Cajon | J75: California | K75: United States | M75: WEEKDAY() | N75: =WEEKDAY(N71,17) -> 6
A76: Topshelf | B76: Eau de Parfum | C76: 139.99 | D76: 10 | E76: 4 | F76: =C:C*E:E -> 559.96 | G76: =IF(Table2[[#This Row],[Sold]]>1000,"High Quality","Normal Quality") -> Normal Quality | H76: 45361.912 | I76: Houston | J76: Texas | K76: United States | M76: DATEDIF() | N76: =DATEDIF(H2,N71,"D") -> 1128
A77: Giorgio Armani | B77: Eau de Toilette | C77: 29.99 | D77: 3 | E77: 61 | F77: =C:C*E:E -> 1829.39 | G77: =IF(Table2[[#This Row],[Sold]]>1000,"High Quality","Normal Quality") -> Normal Quality | H77: 45362.086 | I77: Houston | J77: Texas | K77: United States
A78: Moschino | B78: Eau de Parfum | C78: 35.99 | D78: 10 | E78: 3 | F78: =C:C*E:E -> 107.97 | G78: =IF(Table2[[#This Row],[Sold]]>1000,"High Quality","Normal Quality") -> Normal Quality | H78: 45362.161 | I78: Edison | J78: United States | K78: United States | M78: Vlook up was done in separate sheet to find the price using the brand name.
A79: As Show | B79: Eau de Parfum | C79: 69.99 | D79: 13 | E79: 49 | F79: =C:C*E:E -> 3429.51 | G79: =IF(Table2[[#This Row],[Sold]]>1000,"High Quality","Normal Quality") -> Normal Quality | H79: 45362.188 | I79: Hong Kong | J79: Hong Kong | K79: China | M79: Match and Index is done in seperate page.
A80: Eau de Cologne | B80: Eau de Toilette | C80: 14.99 | D80: 10 | E80: 72 | F80: =C:C*E:E -> 1079.28 | G80: =IF(Table2[[#This Row],[Sold]]>1000,"High Quality","Normal Quality") -> Normal Quality | H80: 45362.318 | I80: Cabot | J80: Arkansas | K80: United States
A81: Michael Malul London | B81: Eau de Parfum | C81: 90.11 | D81: 6 | E81: 51 | F81: =C:C*E:E -> 4595.61 | G81: =IF(Table2[[#This Row],[Sold]]>1000,"High Quality","Normal Quality") -> Normal Quality | H81: 45362.396 | I81: Columbia | J81: South Carolina | K81: United States
A82: Unknownves Saint Laurent | B82: Eau de Parfum | C82: 15.99 | D82: 9 | E82: 91 | F82: =C:C*E:E -> 1455.09 | G82: =IF(Table2[[#This Row],[Sold]]>1000,"High Quality","Normal Quality") -> Normal Quality | H82: 45362.401 | I82: New York | J82: New York | K82: United States
A83: Heaven Scents | B83: Eau de Parfum | C83: 139.99 | D83: 16 | E83: 46 | F83: =C:C*E:E -> 6439.54 | G83: =IF(Table2[[#This Row],[Sold]]>1000,"High Quality","Normal Quality") -> Normal Quality | H83: 45362.632 | I83: Bridgeview | J83: Illinois | K83: United States
A84: Cartier | B84: Eau de Toilette | C84: 49.52 | D84: 31 | E84: 20 | F84: =C:C*E:E -> 990.4 | G84: =IF(Table2[[#This Row],[Sold]]>1000,"High Quality","Normal Quality") -> Normal Quality | H84: 45362.865 | I84: Hackensack | J84: New York | K84: United States
A85: Jacques Bogart | B85: Eau de Toilette | C85: 13.97 | D85: 6 | E85: 957 | F85: =C:C*E:E -> 13369.29 | G85: =IF(Table2[[#This Row],[Sold]]>1000,"High Quality","Normal Quality") -> Normal Quality | H85: 45362.988 | I85: Dallas | J85: Texas | K85: United States
A86: Dolce&Gabbana | B86: Eau de Toilette | C86: 34.99 | D86: 0 | E86: 48 | F86: =C:C*E:E -> 1679.52 | G86: =IF(Table2[[#This Row],[Sold]]>1000,"High Quality","Normal Quality") -> Normal Quality | H86: 45363.39 | I86: Pomona | J86: California | K86: Hong Kong
A87: Armaf | B87: Eau de Parfum | C87: 28.8 | D87: 83 | E87: 712 | F87: =C:C*E:E -> 20505.6 | G87: =IF(Table2[[#This Row],[Sold]]>1000,"High Quality","Normal Quality") -> Normal Quality | H87: 45363.678 | I87: Brooklyn | J87: New York | K87: United States
A88: Ralph Lauren | B88: Eau de Toilette | C88: 22.99 | D88: 3 | E88: 14 | F88: =C:C*E:E -> 321.86 | G88: =IF(Table2[[#This Row],[Sold]]>1000,"High Quality","Normal Quality") -> Normal Quality | H88: 45363.713 | I88: Brooklyn | J88: New York | K88: United States
A89: Giorgio Armani | B89: Eau de Parfum | C89: 25.95 | D89: 10 | E89: 280 | F89: =C:C*E:E -> 7266 | G89: =IF(Table2[[#This Row],[Sold]]>1000,"High Quality","Normal Quality") -> Normal Quality | H89: 45363.716 | I89: Stafford | J89: Texas | K89: United States
A90: As Showed | B90: Eau de Toilette | C90: 43.47 | D90: 49 | E90: 34 | F90: =C:C*E:E -> 1477.98 | G90: =IF(Table2[[#This Row],[Sold]]>1000,"High Quality","Normal Quality") -> Normal Quality | H90: 45363.736 | I90: Hong Kong Or Virginia | J90: Hong Kong | K90: China
A91: Classic Brands | B91: Eau de Cologne | C91: 17.89 | D91: 10 | E91: 2256 | F91: =C:C*E:E -> 40359.84 | G91: =IF(Table2[[#This Row],[Sold]]>1000,"High Quality","Normal Quality") -> High Quality | H91: 45363.755 | I91: Winter Garden | J91: Florida | K91: United States
... A1001: Dolce&Gabbana | B1001: Eau de Toilette | C1001: 27.99 | D1001: 0 | E1001: 24 | F1001: =C:C*E:E -> 671.76 | G1001: =IF(Table2[[#This Row],[Sold]]>1000,"High Quality","Normal Quality") -> Normal Quality | H1001: 45378 | I1001: Des Moines | J1001: Iowa | K1001: United States

Sheet vlook up
A1: Branded | B1: Type | C1: Price with Currency | D1: Available Stock | E1: Sold | F1: Parfum Quality | G1: Finding price using brand name
A2: Alexandria Eau de Parfum | B2: Eau de Parfum | C2: 3 | D2: 57 | E2: 4 | F2: Normal Quality | G2: =VLOOKUP(Table19[[#This Row],[Branded]],'vlook up'!A1:F68,3,FALSE) -> 3
A3: Eau de Parfum | B3: Eau de Parfum | C3: 3.5 | D3: 0 | E3: 3009 | F3: High Quality | G3: =VLOOKUP(Table19[[#This Row],[Branded]],'vlook up'!A2:F69,3,FALSE) -> 3.5
A4: 2Nd To None | B4: Eau de Parfum | C4: 6.65 | D4: 10 | E4: 18882 | F4: High Quality | G4: =VLOOKUP(Table19[[#This Row],[Branded]],'vlook up'!A3:F70,3,FALSE) -> 6.65
A5: Afnan | B5: Eau de Parfum | C5: 6.94 | D5: 10 | E5: 131 | F5: Normal Quality | G5: =VLOOKUP(Table19[[#This Row],[Branded]],'vlook up'!A4:F71,3,FALSE) -> 6.94
A6: Secertmu | B6: Eau de Parfum | C6: 6.96 | D6: 3 | E6: 102 | F6: Normal Quality | G6: =VLOOKUP(Table19[[#This Row],[Branded]],'vlook up'!A5:F72,3,FALSE) -> 6.96
A7: Secertmu | B7: Eau de Parfum | C7: 6.97 | D7: 10 | E7: 803 | F7: Normal Quality | G7: =VLOOKUP(Table19[[#This Row],[Branded]],'vlook up'!A6:F73,3,FALSE) -> 6.96
A8: Unbranded | B8: Car Air Freshener | C8: 7.19 | D8: 10 | E8: 131 | F8: Normal Quality | G8: =VLOOKUP(Table19[[#This Row],[Branded]],'vlook up'!A7:F74,3,FALSE) -> 7.19
A9: Pierre Cardin | B9: Eau de Toilette | C9: 7.28 | D9: 3 | E9: 149 | F9: Normal Quality | G9: =VLOOKUP(Table19[[#This Row],[Branded]],'vlook up'!A8:F75,3,FALSE) -> 7.28
A10: Dolce & Gabbana | B10: Eau de Parfum | C10: 7.5 | D10: 24 | E10: 115 | F10: Normal Quality | G10: =VLOOKUP(Table19[[#This Row],[Branded]],'vlook up'!A9:F76,3,FALSE) -> 7.5
A11: BurberrUnknown | B11: Eau de Toilette | C11: 7.95 | D11: 10 | E11: 254 | F11: Normal Quality | G11: =VLOOKUP(Table19[[#This Row],[Branded]],'vlook up'!A10:F77,3,FALSE) -> 7.95
A12: Secertmu | B12: Eau de Parfum | C12: 7.96 | D12: 10 | E12: 38 | F12: Normal Quality | G12: =VLOOKUP(Table19[[#This Row],[Branded]],'vlook up'!A11:F78,3,FALSE) -> 7.96
A13: DvUnknownne Eau de Parfum | B13: BodUnknown Oil | C13: 8 | D13: 10 | E13: 1113 | F13: High Quality | G13: =VLOOKUP(Table19[[#This Row],[Branded]],'vlook up'!A12:F79,3,FALSE) -> 8
... A70: Jaguar | B70: Eau de Parfum | C70: 13.15 | D70: 6 | E70: 7 | F70: Normal Quality | G70: =VLOOKUP(Table19[[#This Row],[Branded]],'vlook up'!A69:F136,3,FALSE) -> 13.15

Sheet Forecasting the sale
A1: Timeline | B1: Values | C1: Forecast | D1: Lower Confidence Bound | E1: Upper Confidence Bound
A2: 45292 | B2: 45292
A3: 45293 | B3: 45293
A4: 45294 | B4: 45294
A5: 45295 | B5: 45295
A6: 45296 | B6: 45296
A7: 45297 | B7: 45297
A8: 45298 | B8: 45298
A9: 45299 | B9: 45299
A10: 45300 | B10: 45300
A11: 45301 | B11: 45301
A12: 45302 | B12: 45302
A13: 45303 | B13: 45303
... A182: 45472 | B182: 45472
A183: 45473 | B183: 45473 | C183: 45473 | D183: 45473 | E183: 45473
A184: 45474 | C184: =_xlfn.FORECAST.ETS(A184,$B$2:$B$183,$A$2:$A$183,1,1) -> 45474 | D184: =C184-_xlfn.FORECAST.ETS.CONFINT(A184,$B$2:$B$183,$A$2:$A$183,0.95,1,1) -> 45474 | E184: =C184+_xlfn.FORECAST.ETS.CONFINT(A184,$B$2:$B$183,$A$2:$A$183,0.95,1,1) -> 45474
A185: 45475 | C185: =_xlfn.FORECAST.ETS(A185,$B$2:$B$183,$A$2:$A$183,1,1) -> 45475 | D185: =C185-_xlfn.FORECAST.ETS.CONFINT(A185,$B$2:$B$183,$A$2:$A$183,0.95,1,1) -> 45475 | E185: =C185+_xlfn.FORECAST.ETS.CONFINT(A185,$B$2:$B$183,$A$2:$A$183,0.95,1,1) -> 45475
A186: 45476 | C186: =_xlfn.FORECAST.ETS(A186,$B$2:$B$183,$A$2:$A$183,1,1) -> 45476 | D186: =C186-_xlfn.FORECAST.ETS.CONFINT(A186,$B$2:$B$183,$A$2:$A$183,0.95,1,1) -> 45476 | E186: =C186+_xlfn.FORECAST.ETS.CONFINT(A186,$B$2:$B$183,$A$2:$A$183,0.95,1,1) -> 45476
A187: 45477 | C187: =_xlfn.FORECAST.ETS(A187,$B$2:$B$183,$A$2:$A$183,1,1) -> 45477 | D187: =C187-_xlfn.FORECAST.ETS.CONFINT(A187,$B$2:$B$183,$A$2:$A$183,0.95,1,1) -> 45477 | E187: =C187+_xlfn.FORECAST.ETS.CONFINT(A187,$B$2:$B$183,$A$2:$A$183,0.95,1,1) -> 45477
A188: 45478 | C188: =_xlfn.FORECAST.ETS(A188,$B$2:$B$183,$A$2:$A$183,1,1) -> 45478 | D188: =C188-_xlfn.FORECAST.ETS.CONFINT(A188,$B$2:$B$183,$A$2:$A$183,0.95,1,1) -> 45478 | E188: =C188+_xlfn.FORECAST.ETS.CONFINT(A188,$B$2:$B$183,$A$2:$A$183,0.95,1,1) -> 45478
A189: 45479 | C189: =_xlfn.FORECAST.ETS(A189,$B$2:$B$183,$A$2:$A$183,1,1) -> 45479 | D189: =C189-_xlfn.FORECAST.ETS.CONFINT(A189,$B$2:$B$183,$A$2:$A$183,0.95,1,1) -> 45479 | E189: =C189+_xlfn.FORECAST.ETS.CONFINT(A189,$B$2:$B$183,$A$2:$A$183,0.95,1,1) -> 45479
A190: 45480 | C190: =_xlfn.FORECAST.ETS(A190,$B$2:$B$183,$A$2:$A$183,1,1) -> 45480 | D190: =C190-_xlfn.FORECAST.ETS.CONFINT(A190,$B$2:$B$183,$A$2:$A$183,0.95,1,1) -> 45480 | E190: =C190+_xlfn.FORECAST.ETS.CONFINT(A190,$B$2:$B$183,$A$2:$A$183,0.95,1,1) -> 45480
A191: 45481 | C191: =_xlfn.FORECAST.ETS(A191,$B$2:$B$183,$A$2:$A$183,1,1) -> 45481 | D191: =C191-_xlfn.FORECAST.ETS.CONFINT(A191,$B$2:$B$183,$A$2:$A$183,0.95,1,1) -> 45481 | E191: =C191+_xlfn.FORECAST.ETS.CONFINT(A191,$B$2:$B$183,$A$2:$A$183,0.95,1,1) -> 45481
A192: 45482 | C192: =_xlfn.FORECAST.ETS(A192,$B$2:$B$183,$A$2:$A$183,1,1) -> 45482 | D192: =C192-_xlfn.FORECAST.ETS.CONFINT(A192,$B$2:$B$183,$A$2:$A$183,0.95,1,1) -> 45482 | E192: =C192+_xlfn.FORECAST.ETS.CONFINT(A192,$B$2:$B$183,$A$2:$A$183,0.95,1,1) -> 45482
A193: 45483 | C193: =_xlfn.FORECAST.ETS(A193,$B$2:$B$183,$A$2:$A$183,1,1) -> 45483 | D193: =C193-_xlfn.FORECAST.ETS.CONFINT(A193,$B$2:$B$183,$A$2:$A$183,0.95,1,1) -> 45483 | E193: =C193+_xlfn.FORECAST.ETS.CONFINT(A193,$B$2:$B$183,$A$2:$A$183,0.95,1,1) -> 45483
A194: 45484 | C194: =_xlfn.FORECAST.ETS(A194,$B$2:$B$183,$A$2:$A$183,1,1) -> 45484 | D194: =C194-_xlfn.FORECAST.ETS.CONFINT(A194,$B$2:$B$183,$A$2:$A$183,0.95,1,1) -> 45484 | E194: =C194+_xlfn.FORECAST.ETS.CONFINT(A194,$B$2:$B$183,$A$2:$A$183,0.95,1,1) -> 45484
A195: 45485 | C195: =_xlfn.FORECAST.ETS(A195,$B$2:$B$183,$A$2:$A$183,1,1) -> 45485 | D195: =C195-_xlfn.FORECAST.ETS.CONFINT(A195,$B$2:$B$183,$A$2:$A$183,0.95,1,1) -> 45485 | E195: =C195+_xlfn.FORECAST.ETS.CONFINT(A195,$B$2:$B$183,$A$2:$A$183,0.95,1,1) -> 45485
... A244: 45534 | C244: =_xlfn.FORECAST.ETS(A244,$B$2:$B$183,$A$2:$A$183,1,1) -> 45534 | D244: =C244-_xlfn.FORECAST.ETS.CONFINT(A244,$B$2:$B$183,$A$2:$A$183,0.95,1,1) -> 45534 | E244: =C244+_xlfn.FORECAST.ETS.CONFINT(A244,$B$2:$B$183,$A$2:$A$183,0.95,1,1) -> 45534

Sheet Sheet1
B1: Available Stock | C1: Sold | D1: Revenue
A2: =RANDBETWEEN(DATE(2024,1,1),(DATE(2024,6,30))) -> 45343 | B2: 0 | C2: 45 | D2: 2474.55
A3: =RANDBETWEEN(DATE(2024,1,1),(DATE(2024,6,30))) -> 45371 | B3: 0 | C3: 75 | D3: 2099.25
A4: =RANDBETWEEN(DATE(2024,1,1),(DATE(2024,6,30))) -> 45374 | B4: 8 | C4: 69 | D4: 1169.55
A5: =RANDBETWEEN(DATE(2024,1,1),(DATE(2024,6,30))) -> 45367 | B5: 8 | C5: 1 | D5: 34.99
A6: =RANDBETWEEN(DATE(2024,1,1),(DATE(2024,6,30))) -> 45388 | B6: 0 | C6: 331 | D6: 6586.9
A7: =RANDBETWEEN(DATE(2024,1,1),(DATE(2024,6,30))) -> 45371 | B7: 6 | C7: 37 | D7: 1905.13
A8: =RANDBETWEEN(DATE(2024,1,1),(DATE(2024,6,30))) -> 45374 | B8: 10 | C8: 286 | D8: 6292
A9: =RANDBETWEEN(DATE(2024,1,1),(DATE(2024,6,30))) -> 45410 | B9: 3 | C9: 40 | D9: 1599.6
A10: =RANDBETWEEN(DATE(2024,1,1),(DATE(2024,6,30))) -> 45471 | B10: 9 | C10: 647 | D10: 9698.53
A11: =RANDBETWEEN(DATE(2024,1,1),(DATE(2024,6,30))) -> 45345 | B11: 0 | C11: 9 | D11: 1620
A12: =RANDBETWEEN(DATE(2024,1,1),(DATE(2024,6,30))) -> 45312 | B12: 10 | C12: 38 | D12: 302.48
A13: =RANDBETWEEN(DATE(2024,1,1),(DATE(2024,6,30))) -> 45347 | B13: 3 | C13: 30 | D13: 478.5
... A1001: =RANDBETWEEN(DATE(2024,1,1),(DATE(2024,6,30))) -> 45457 | B1001: 0 | C1001: 24 | D1001: 671.76
